classenv/__init__.py
classenv/decorator.py
classenv/models/__init__.py
classenv/models/base_config.py
classenv/models/parsed_config.py
classenv/models/raw_config.py
classenv/types.py
classenv-1.1.0.dist-info/LICENSE
classenv-1.1.0.dist-info/METADATA
classenv-1.1.0.dist-info/WHEEL
classenv-1.1.0.dist-info/RECORD
