Metadata-Version: 2.1
Name: classenv
Version: 1.1.0
Summary: Use a decorator to specify environment variables with automatic type parsing!
License: MIT
Author: Dogeek
Author-email: simon.bordeyne@gmail.com
Requires-Python: >=3.10,<4.0
Classifier: License :: OSI Approved :: MIT License
Classifier: Programming Language :: Python :: 3
Classifier: Programming Language :: Python :: 3.10
Classifier: Programming Language :: Python :: 3.11
Classifier: Programming Language :: Python :: 3.12
Classifier: Programming Language :: Python :: 3.7
Classifier: Programming Language :: Python :: 3.8
Classifier: Programming Language :: Python :: 3.9
